jbar/__init__.py
jbar/widget.js
jbar-0.1.6.dist-info/METADATA
jbar-0.1.6.dist-info/WHEEL
jbar-0.1.6.dist-info/RECORD
